main.py
report_package/__init__.py
report_package/table_racers.py
monaco_report_evheniy_task6-0.1.0.dist-info/METADATA
monaco_report_evheniy_task6-0.1.0.dist-info/WHEEL
monaco_report_evheniy_task6-0.1.0.dist-info/entry_points.txt
monaco_report_evheniy_task6-0.1.0.dist-info/top_level.txt
monaco_report_evheniy_task6-0.1.0.dist-info/RECORD
