Metadata-Version: 2.4
Name: monaco-report-Evheniy-task6
Version: 0.1.0
Summary: A simple report for Monaco 2018 racing
Author-email: Evhen <eolofinskij@gmail.com>
Requires-Python: >=3.10
